cnn_flownet/__init__.py
cnn_flownet/config.py
cnn_flownet/model.py
cnn_flownet/parallel_model.py
cnn_flownet/utils.py
cnn_flownet/visualize.py
densenet/__init__.py
densenet/compute-cifar10-mean.py
densenet/densenet.py
densenet/make_graph.py
densenet/plot.py
densenet/train.py
denseunet/__init__.py
denseunet/dense_unet.py
example_pkg/__init__.py
flownet/__init__.py
flownet/corr.py
flownet/test.py
flownet/src/__init__.py
flownet/src/correlation.py
flownet/src/dataloader.py
flownet/src/dataset_configs.py
flownet/src/downsample.py
flownet/src/flow_warp.py
flownet/src/flowlib.py
flownet/src/net.py
flownet/src/training_schedules.py
flownet/src/utils.py
flownet/src/flownet2/__init__.py
flownet/src/flownet2/flownet2.py
flownet/src/flownet2/test.py
flownet/src/flownet2/train.py
flownet/src/flownet_c/__init__.py
flownet/src/flownet_c/flownet_c.py
flownet/src/flownet_c/test.py
flownet/src/flownet_c/train.py
flownet/src/flownet_cs/__init__.py
flownet/src/flownet_cs/flownet_cs.py
flownet/src/flownet_cs/test.py
flownet/src/flownet_cs/train.py
flownet/src/flownet_css/__init__.py
flownet/src/flownet_css/flownet_css.py
flownet/src/flownet_css/test.py
flownet/src/flownet_css/train.py
flownet/src/flownet_s/__init__.py
flownet/src/flownet_s/flownet_s.py
flownet/src/flownet_s/test.py
flownet/src/flownet_s/train.py
flownet/src/flownet_sd/__init__.py
flownet/src/flownet_sd/flownet_sd.py
flownet/src/flownet_sd/test.py
flownet/src/flownet_sd/train.py
ffdvn-0.5.18.dist-info/METADATA
ffdvn-0.5.18.dist-info/WHEEL
ffdvn-0.5.18.dist-info/top_level.txt
ffdvn-0.5.18.dist-info/RECORD
